setup.py
make/__init__.py
make/p0rt3r.py
p0rt3r.egg-info/PKG-INFO
p0rt3r.egg-info/SOURCES.txt
p0rt3r.egg-info/dependency_links.txt
p0rt3r.egg-info/top_level.txt