Metadata-Version: 1.0
Name: p0rt3r
Version: 0.0.1
Summary: Simple, efficient, and relatively quick port scanner
Home-page: UNKNOWN
Author: UNKNOWN
Author-email: UNKNOWN
License: UNKNOWN
Platform: UNKNOWN
